ultr_bias_toolkit/__init__.py
ultr_bias_toolkit/bias/__init__.py
ultr_bias_toolkit/bias/intervention_harvesting/__init__.py
ultr_bias_toolkit/bias/intervention_harvesting/adjacent_chain.py
ultr_bias_toolkit/bias/intervention_harvesting/all_pairs.py
ultr_bias_toolkit/bias/intervention_harvesting/pivot.py
ultr_bias_toolkit/bias/intervention_harvesting/util.py
ultr_bias_toolkit/bias/naive.py
ultr_bias_toolkit/util/__init__.py
ultr_bias_toolkit/util/assertions.py
ultr_bias_toolkit-0.0.5.dist-info/METADATA
ultr_bias_toolkit-0.0.5.dist-info/WHEEL
ultr_bias_toolkit-0.0.5.dist-info/RECORD
