Metadata-Version: 2.1
Name: ultr-bias-toolkit
Version: 0.0.5
Summary: Toolkit for bias estimation in unbiased learning to rank
Author: Philipp Hager
Author-email: philipp.konstantin.hager@gmail.com
Requires-Python: >=3.9,<4.0
Classifier: Programming Language :: Python :: 3
Classifier: Programming Language :: Python :: 3.9
Classifier: Programming Language :: Python :: 3.10
Classifier: Programming Language :: Python :: 3.11
Requires-Dist: pandas (>=2.1.4,<3.0.0)
Requires-Dist: torch (>=2.1.1,<3.0.0)
Requires-Dist: tqdm (>=4.66.1,<5.0.0)
